idvpackage/__init__.py
idvpackage/blur_detection.py
idvpackage/common.py
idvpackage/constants.py
idvpackage/ekyc.py
idvpackage/genai_utils.py
idvpackage/iraq_id_extraction.py
idvpackage/iraq_id_extraction_withopenai.py
idvpackage/iraq_passport_extraction.py
idvpackage/jor_passport_extraction.py
idvpackage/lazy_imports.py
idvpackage/lebanon_id_extraction.py
idvpackage/lebanon_passport_extraction.py
idvpackage/liveness_spoofing_v2.py
idvpackage/ocr.py
idvpackage/ocr_utils.py
idvpackage/pse_passport_extraction.py
idvpackage/qatar_id_extraction.py
idvpackage/sau_id_extraction.py
idvpackage/sudan_id_extraction.py
idvpackage/sudan_passport_extraction.py
idvpackage/syr_passport_extraction.py
idvpackage/uae_id_extraction.py
idvpackage/icons/battery1.png
idvpackage/icons/battery3.png
idvpackage/icons/network1.png
idvpackage/icons/network2.png
idvpackage/icons/wifi1.png
idvpackage/icons/wifi3.png
idvpackage/icons/wifi4.png
idvpackage/spoof_resources/2.7_80x80_MiniFASNetV2.pth
idvpackage/spoof_resources/4_0_0_80x80_MiniFASNetV1SE.pth
idvpackage/spoof_resources/MiniFASNet.py
idvpackage/spoof_resources/__init__.py
idvpackage/spoof_resources/functional.py
idvpackage/spoof_resources/generate_patches.py
idvpackage/spoof_resources/transform.py
idvpackage-3.0.11.dist-info/licenses/LICENSE
idvpackage-3.0.11.dist-info/METADATA
idvpackage-3.0.11.dist-info/WHEEL
idvpackage-3.0.11.dist-info/top_level.txt
idvpackage-3.0.11.dist-info/RECORD
