Metadata-Version: 2.4
Name: idvpackage
Version: 3.0.11
Summary: This repository contains a Python program designed to execute Optical Character Recognition (OCR) and Facial Recognition on images.
Home-page: https://github.com/NymCard-Payments/project_idv_package
Classifier: Programming Language :: Python :: 3
Classifier: License :: OSI Approved :: MIT License
Classifier: Operating System :: OS Independent
Requires-Python: >=3.7
License-File: LICENSE
Requires-Dist: setuptools
Requires-Dist: google-cloud-vision
Requires-Dist: opencv-python-headless
Requires-Dist: Pillow
Requires-Dist: numpy
Requires-Dist: cmake
Requires-Dist: face-recognition
Requires-Dist: googletrans==4.0.2
Requires-Dist: rapidfuzz
Requires-Dist: pycountry
Requires-Dist: hijri_converter
Requires-Dist: pytesseract
Requires-Dist: gender-guesser
Requires-Dist: deep-translator
Requires-Dist: dlib==19.24.6
Requires-Dist: deepface
Requires-Dist: tf-keras
Requires-Dist: facenet-pytorch
Requires-Dist: scikit-image
Requires-Dist: google.generativeai==0.8.2
Requires-Dist: openai==2.6.1
Requires-Dist: langchain==0.2.17
Requires-Dist: langchain-community==0.2.19
Requires-Dist: pydantic==1.10.22
Requires-Dist: python-dateutil
Requires-Dist: pyasn1<0.5.0,>=0.4.1
Dynamic: classifier
Dynamic: description
Dynamic: description-content-type
Dynamic: home-page
Dynamic: license-file
Dynamic: requires-dist
Dynamic: requires-python
Dynamic: summary
